FNNH.py
FNNH-0.0.6.dist-info/METADATA
FNNH-0.0.6.dist-info/WHEEL
FNNH-0.0.6.dist-info/license.txt
FNNH-0.0.6.dist-info/top_level.txt
FNNH-0.0.6.dist-info/RECORD
