Metadata-Version: 2.1
Name: FNNH
Version: 0.0.6
Summary: A flexible CNN based Hash Function
Home-page: https://github.com/apratimr/fnn-hash
Author: Apratim Ray
Author-email: apratimr55@gmail.com
License: UNKNOWN
Platform: UNKNOWN
Classifier: Programming Language :: Python :: 3
Classifier: License :: OSI Approved :: GNU General Public License v3 (GPLv3)
Classifier: Operating System :: OS Independent
Requires-Python: >=3.6
Requires-Dist: numpy
